mlops_project/__init__.py
mlops_project/config.py
mlops_project/dataset.py
mlops_project/features.py
mlops_project/plots.py
mlops_project/modeling/__init__.py
mlops_project/modeling/predict.py
mlops_project/modeling/train.py
mlops_project-0.0.4.dist-info/licenses/LICENSE
mlops_project-0.0.4.dist-info/WHEEL
mlops_project-0.0.4.dist-info/METADATA
mlops_project-0.0.4.dist-info/RECORD
