Metadata-Version: 2.4
Name: mlops_project
Version: 0.0.4
Summary: Семестровый проект по MLOps
Author: Chervonikov Alexey
Requires-Python: ~=3.12
Classifier: Programming Language :: Python :: 3
Classifier: License :: OSI Approved :: MIT License
License-File: LICENSE
Requires-Dist: numpy==1.26.4
Requires-Dist: pandas==2.2.2
Requires-Dist: torch==2.4.0
Requires-Dist: matplotlib==3.9.2
Project-URL: Homepage, https://gitlab.v-efimov.tech/mlops_spring_2025/mlops_project_a.chervonikov/
